{
  "titel": "Kompetenzunsicherheit",
  "definition": "Bedenken, dass im Unternehmen die notwendigen Fachkenntnisse für neue Technologien oder Innovationsansätze fehlen, verbunden mit Unsicherheit bei der strategischen Mitarbeiterentwicklung und Talentakquise für zukunftsrelevante Kompetenzen.",
  "ursachen": {
    "psychologische_faktoren": [
      {
        "name": "Impostor-Syndrom auf Organisationsebene",
        "beschreibung": "Kollektive Selbstzweifel an den eigenen Fähigkeiten trotz objektiv vorhandener Kompetenzen"
      },
      {
        "name": "Überschätzung externer Expertise",
        "beschreibung": "Glaube, dass Wettbewerber oder Startups über überlegenes Wissen verfügen"
      },
      {
        "name": "Technologie-Angst",
        "beschreibung": "Diffuse Bedenken gegenüber Komplexität und rascher Entwicklung neuer Technologien"
      },
      {
        "name": "Perfektionismusstreben",
        "beschreibung": "Überhöhte Anforderungen an die Vollständigkeit von Kompetenzen vor Innovationsschritten"
      }
    ],
    "strukturelle_faktoren": [
      {
        "name": "Unzureichende Kompetenzerfassung",
        "beschreibung": "Fehlende systematische Erfassung und Visualisierung vorhandener Kompetenzen im Unternehmen"
      },
      {
        "name": "Traditionelle Personalentwicklung",
        "beschreibung": "Vergangenheitsorientierten Schulungsprogramme statt zukunftsorientierter Kompetenzentwicklung"
      },
      {
        "name": "Silodenken",
        "beschreibung": "Mangelnder Wissensaustausch zwischen Abteilungen und hierarchischen Ebenen"
      },
      {
        "name": "Unklare Technologiestrategie",
        "beschreibung": "Fehlende Priorisierung zukünftiger Technologiefelder und benötigter Kompetenzen"
      }
    ]
  },
  "symptome_und_auswirkungen": {
    "erkennungsmerkmale": [
      "Übermäßiger Einsatz externer Berater auch für strategische Kernkompetenzen",
      "Häufige Verweise auf mangelndes Know-how als Begründung für Innovationszurückhaltung",
      "Parallele, unkoordinierte Weiterbildungsinitiativen ohne strategischen Fokus",
      "Geringe Experimentierfreude mit neuen Technologien",
      "Zögerliche Besetzung von Schlüsselpositionen aufgrund überhöhter Anforderungsprofile"
    ],
    "negative_folgen": [
      {
        "name": "Innovations-Paralyse",
        "beschreibung": "Blockade von Innovationsinitiativen aufgrund von Kompetenzbedenken"
      },
      {
        "name": "Kompetenz-Exodus",
        "beschreibung": "Abwanderung talentierter Mitarbeiter, die ihre Fähigkeiten nicht einbringen können"
      },
      {
        "name": "Technologischer Rückstand",
        "beschreibung": "Wachsende Lücke zwischen verfügbaren und genutzten Technologien"
      },
      {
        "name": "Abhängigkeit von externen Dienstleistern",
        "beschreibung": "Verlust von Kernkompetenzen durch übermäßiges Outsourcing"
      }
    ]
  },
  "loesungsansaetze": {
    "methodische_ansaetze": [
      {
        "name": "Kompetenz-Mapping",
        "beschreibung": "Systematische Erfassung und Visualisierung vorhandener und benötigter Kompetenzen"
      },
      {
        "name": "Strategic Workforce Planning",
        "beschreibung": "Langfristige, an der Unternehmensstrategie ausgerichtete Personalplanung"
      },
      {
        "name": "Learning Expeditions",
        "beschreibung": "Gezielte Exkursionen zu Innovationsführern zur Inspiration und zum Abbau von Berührungsängsten"
      },
      {
        "name": "Micro-Learning-Strategie",
        "beschreibung": "Kleinteilige, kontinuierliche Lernformate statt umfangreicher, zeitintensiver Schulungsprogramme"
      }
    ],
    "kulturelle_veraenderungen": [
      {
        "name": "Learning Organization",
        "beschreibung": "Etablierung einer Kultur, die kontinuierliches Lernen als Kernwert verankert"
      },
      {
        "name": "Reverse Mentoring",
        "beschreibung": "Jüngere Mitarbeiter schulen Führungskräfte in neuen Technologien und Trends"
      },
      {
        "name": "T-Shape-Mitarbeiterentwicklung",
        "beschreibung": "Förderung von Tiefenexpertise in Kombination mit breitem Querschnittswissen"
      },
      {
        "name": "Fehlertolerante Lernkultur",
        "beschreibung": "Akzeptanz von Fehlern beim Erlernen und Anwenden neuer Kompetenzen"
      }
    ],
    "unterstuetzende_tools": [
      {
        "name": "Skill-Management-Plattformen",
        "beschreibung": "Digitale Werkzeuge zur Erfassung, Visualisierung und Entwicklung von Kompetenzen"
      },
      {
        "name": "Learning Experience Platforms",
        "beschreibung": "Moderne Lernplattformen mit personalisierten, adaptiven Lernangeboten"
      },
      {
        "name": "Communities of Practice",
        "beschreibung": "Digitale und physische Räume für den Austausch zu speziellen Fachthemen"
      },
      {
        "name": "Micro-Credentials",
        "beschreibung": "Digitale Nachweise für kleinere Lerneinheiten zur Sichtbarmachung von Kompetenzentwicklung"
      }
    ]
  },
  "best_practices": {
    "erfolgreiche_beispiele": [
      {
        "name": "AT&T",
        "beschreibung": "Future Ready Workforce Initiative mit $1 Mrd. Investment in Umschulung für digitale Kompetenzen"
      },
      {
        "name": "IBM",
        "beschreibung": "SkillsBuild-Plattform mit KI-gestützten Lernpfaden und personalisierten Empfehlungen"
      },
      {
        "name": "Siemens",
        "beschreibung": "Learning Campus mit kombinierten internen und externen Lernangeboten für Zukunftskompetenzen"
      }
    ],
    "praktische_tipps": [
      "Beginne mit einer transparenten Bestandsaufnahme vorhandener Kompetenzen ohne Schuldzuweisungen",
      "Fokussiere auf 'evergreen skills' wie kritisches Denken neben technischen Fachkompetenzen",
      "Schaffe direkte Anwendungsmöglichkeiten für neu erworbene Kompetenzen in konkreten Projekten",
      "Entwickle Führungskräfte zu Coaches für kontinuierliches Lernen statt zu reinen Wissensvermittlern",
      "Etabliere ein System zur frühzeitigen Erkennung von Kompetenzbedarfen durch Technologie-Scouting"
    ]
  },
  "quellen": [
    {
      "autor": "Peter M. Senge",
      "titel": "The Fifth Discipline: The Art & Practice of The Learning Organization"
    },
    {
      "autor": "Alvin Toffler",
      "titel": "Future Shock"
    },
    {
      "autor": "Reid Hoffman & Chris Yeh",
      "titel": "Blitzscaling: The Lightning-Fast Path to Building Massively Valuable Companies"
    },
    {
      "autor": "Josh Bersin",
      "titel": "Irresistible: The Seven Secrets of the World's Most Enduring, Employee-Focused Organizations"
    }
  ]
}